{
  "main": {
    "id": "479125a28ee067a1",
    "type": "split",
    "children": [
      {
        "id": "188e0b0464292b01",
        "type": "tabs",
        "children": [
          {
            "id": "d43440a72d3a8f2e",
            "type": "leaf",
            "state": {
              "type": "markdown",
              "state": {
                "file": "Pentest/Основные категории/2 Виды атак и уязвимостей/На Веб-приложение/Раскрытие информации/Методика поиска и развития раскрытия информации.md",
                "mode": "source",
                "source": false
              },
              "icon": "lucide-file",
              "title": "Методика поиска и развития раскрытия информации"
            }
          },
          {
            "id": "b27fc20afe0574e6",
            "type": "leaf",
            "state": {
              "type": "markdown",
              "state": {
                "file": "Pentest/Основные категории/2 Виды атак и уязвимостей/На Веб-приложение/Раскрытие информации/Доп. информация/Как найти и использовать уязвимости раскрытия информации.md",
                "mode": "source",
                "source": false
              },
              "icon": "lucide-file",
              "title": "Как найти и использовать уязвимости раскрытия информации"
            }
          }
        ]
      }
    ],
    "direction": "vertical"
  },
  "left": {
    "id": "e57c5e9ecee75335",
    "type": "split",
    "children": [
      {
        "id": "ebcd28e42c9dc9a4",
        "type": "tabs",
        "children": [
          {
            "id": "f52ac7390f9cfa4d",
            "type": "leaf",
            "state": {
              "type": "file-explorer",
              "state": {
                "sortOrder": "alphabetical"
              },
              "icon": "lucide-folder-closed",
              "title": "Файловый менеджер"
            }
          },
          {
            "id": "8d997847aa09be5c",
            "type": "leaf",
            "state": {
              "type": "search",
              "state": {
                "query": "",
                "matchingCase": false,
                "explainSearch": false,
                "collapseAll": false,
                "extraContext": false,
                "sortOrder": "alphabetical"
              },
              "icon": "lucide-search",
              "title": "Поиск"
            }
          },
          {
            "id": "3c6bd971a8a12aeb",
            "type": "leaf",
            "state": {
              "type": "bookmarks",
              "state": {},
              "icon": "lucide-bookmark",
              "title": "Закладки"
            }
          },
          {
            "id": "93a34146b3c863dd",
            "type": "leaf",
            "state": {
              "type": "markdown",
              "state": {
                "file": "Pentest/Основные категории/2 Виды атак и уязвимостей/На Веб-приложение/Инъекции/RCE (инъекция команд OC)/RCE (инъекция команд ОС).md",
                "mode": "source",
                "source": false
              },
              "icon": "lucide-file",
              "title": "RCE (инъекция команд ОС)"
            }
          }
        ]
      }
    ],
    "direction": "horizontal",
    "width": 457.5
  },
  "right": {
    "id": "697c1ae495631f7e",
    "type": "split",
    "children": [
      {
        "id": "069eff8efffecac2",
        "type": "tabs",
        "children": [
          {
            "id": "4b70b2c00e88e7b0",
            "type": "leaf",
            "state": {
              "type": "backlink",
              "state": {
                "file": "Компьютерные сети/Уровни моделей/Подуровень канального уровня (управление доступом к среде).md",
                "collapseAll": false,
                "extraContext": false,
                "sortOrder": "alphabetical",
                "showSearch": false,
                "searchQuery": "",
                "backlinkCollapsed": false,
                "unlinkedCollapsed": true
              },
              "icon": "links-coming-in",
              "title": "Обратные ссылки для Подуровень канального уровня (управление доступом к среде)"
            }
          },
          {
            "id": "51493deec3a7e4f7",
            "type": "leaf",
            "state": {
              "type": "outgoing-link",
              "state": {
                "file": "Компьютерные сети/Уровни моделей/Подуровень канального уровня (управление доступом к среде).md",
                "linksCollapsed": false,
                "unlinkedCollapsed": true
              },
              "icon": "links-going-out",
              "title": "Исходящие ссылки из Подуровень канального уровня (управление доступом к среде)"
            }
          },
          {
            "id": "be22a70a45c21695",
            "type": "leaf",
            "state": {
              "type": "tag",
              "state": {
                "sortOrder": "frequency",
                "useHierarchy": false
              },
              "icon": "lucide-tags",
              "title": "Теги"
            }
          },
          {
            "id": "a0f760479cfe5751",
            "type": "leaf",
            "state": {
              "type": "outline",
              "state": {},
              "icon": "lucide-list",
              "title": "Структура"
            }
          }
        ],
        "currentTab": 3
      }
    ],
    "direction": "horizontal",
    "width": 300,
    "collapsed": true
  },
  "left-ribbon": {
    "hiddenItems": {
      "switcher:Меню быстрого перехода": false,
      "canvas:Создать новый холст": false,
      "graph:Граф": false,
      "daily-notes:Сегодняшняя заметка": false,
      "templates:Вставить шаблон": false,
      "command-palette:Открыть палитру команд": false,
      "publish:Публикация изменений": false
    }
  },
  "active": "d43440a72d3a8f2e",
  "lastOpenFiles": [
    "Pentest/Основные категории/2 Виды атак и уязвимостей/На Веб-приложение/Раскрытие информации/Доп. информация/Как найти и использовать уязвимости раскрытия информации.md",
    "Pentest/Основные категории/2 Виды атак и уязвимостей/На Веб-приложение/Раскрытие информации/Методика поиска и развития раскрытия информации.md",
    "Pentest/Основные категории/2 Виды атак и уязвимостей/На Веб-приложение/Раскрытие информации/Уязвимости раскрытия информации.md",
    "Linux/Администрирования системы/Привилегии/Привилегии.md",
    "Pentest/Основные категории/2 Виды атак и уязвимостей/Виды атак.md",
    "Pentest/Основные категории/2 Виды атак и уязвимостей/На Веб-приложение/Раскрытие информации/Доп. информация",
    "Pentest/Основные категории/2 Виды атак и уязвимостей/Аутентификация/Доп. информация/Уязвимости входа в систему по паролю.md",
    "Pentest/Лабы по portswigger/XXE/Лаборатория эксплуатация Xinclude для получения файлов.md",
    "Pentest/Лабы по portswigger/Уязвимость загрузки файлов/Лабораторная работа Загрузка веб-оболочки через обход пути.md",
    "Pentest/Основные категории/2 Виды атак и уязвимостей/На Веб-приложение/Раскрытие информации",
    "Pentest/Лабы по portswigger/XXE/Лаборатория слепой XXE с внеполосной взаимодействием через объекты XML-параметры.md",
    "Pentest/Лабы по portswigger/XXE/Лаборатория эксплуатация XXE для получения данных путем переопределения локального DTD.md",
    "Pentest/Лабы по portswigger/XXE/Лаборатория эксплуатируя Blind XXE для получения данных с помощью сообщений об ошибках.md",
    "Pentest/Лабы по portswigger/XXE/Лабораторная работа Эксплуатация слепого XXE для извлечения данных с использованием вредоносного внешнего DTD.md",
    "Pentest/Лабы по portswigger/XXE/Лабораторная работа слепой XXE с внеполосным взаимодействием.md",
    "Pentest/Лабы по portswigger/XXE/Лаборатория эксплуатация xxe через загрузку файла изображения.md",
    "Pentest/Лабы по portswigger/Уязвимость загрузки файлов/Лабораторная работа Загрузка веб-оболочки через запутанное расширение файла.md",
    "Pentest/Лабы по portswigger/API/Лабораторная работа Использование загрязнения параметров на стороне сервера в строке запроса.md",
    "Pentest/Лабы по portswigger/API/Лаборатория поиск и использование неиспользованной конечной точки API.md",
    "Pentest/Основные категории/2.1 Инструменты/Брутфорс/Инструмент httpx.md",
    "Pentest/Основные категории/2.1 Инструменты/Инструменты.md",
    "Pentest/Основные категории/2.1 Инструменты/Разведка/Инструмент fuff.md",
    "Pentest/Основные категории/2.1 Инструменты/Брутфорс/Инструмент gobuster.md",
    "Pentest/Основные категории/2.1 Инструменты/Разведка/Инструмент Nmap (Network Mapper).md",
    "Pentest/Основные категории/2.1 Инструменты/Хранилища полезной нагрузки/Хранилище SecLists.md",
    "Pentest/_методики работы/Сбор всех методичек/Список методичек и этапы тестирования.md",
    "Pentest/Основные категории/2.1 Инструменты/Дополнительные источники.md",
    "Pentest/Основные категории/2 Виды атак и уязвимостей/Смежные уязвимости/Уязвимости бизнес-логики/Методика поиска и развития уязвимостей в бизнес логике.md",
    "_Изображения/Изображения pentest/Pasted image 20250316185902.png",
    "Pentest/Основные категории/2.1 Инструменты/Хранилища полезной нагрузки",
    "Linux/Администрирования системы/Фаервол, межсетевые экраны",
    "Linux/Администрирования системы/Планировщик задач cron",
    "Pentest/Основные категории/2 Виды атак и уязвимостей/На Веб-приложение/Инъекции/SQL/Методичка по поиску и развитию уязвимости",
    "Без названия.canvas",
    "Pentest/Основные категории/2 Виды атак и уязвимостей/На Веб-приложение/Инъекции/RCE (инъекция команд OC)",
    "Pentest/_методики работы/Сбор всех методичек",
    "Pentest/Основные категории/2 Виды атак и уязвимостей/Смежные уязвимости/Прохождения пути",
    "_Изображения/Изображения лаборатории по пентесту/Pasted image 20250307150847.png",
    "Pentest/Основные категории/2 Виды атак и уязвимостей/Смежные уязвимости",
    "_Изображения/Изображения Linux/Pasted image 20250227153346.png",
    "_Изображения/Изображения Linux/Pasted image 20250227144737.png",
    "_Изображения/Изображения Linux/Pasted image 20250227144417.png",
    "_Изображения/Изображения Linux/Pasted image 20250227140353.png",
    "_Изображения/Изображения Linux/Pasted image 20250227140011.png",
    "_Изображения/Изображения Linux/Pasted image 20250227135659.png",
    "_Изображения/Изображения Linux/Pasted image 20250227135317.png",
    "_Изображения/Изображения Linux/Pasted image 20250227135426.png",
    "Без названия 1.canvas",
    "Без названия 2.canvas"
  ]
}